hateyugemu/__init__.py
hateyugemu/__main__.py
hateyugemu/main.py
hateyugemu/notify.py
hateyugemu/settings.py
hateyugemu/utils.py
hateyugemu/data/tokens.txt
hateyugemu/data/topics.csv
hateyugemu-0.0.3.dist-info/LICENSE
hateyugemu-0.0.3.dist-info/METADATA
hateyugemu-0.0.3.dist-info/WHEEL
hateyugemu-0.0.3.dist-info/top_level.txt
hateyugemu-0.0.3.dist-info/RECORD
